<xml xmlns="http://www.w3.org/1999/xhtml"><block type="niryo_one_comment" id="D0.RU,,46E5]c#1E2z(Q" x="230" y="30"><field name="COMMENT_TEXT">home/Start Positon</field><next><block type="niryo_one_move_joints_from_joints" id="#iNR?8:)+Db^1ZJkyH$A"><value name="JOINTS"><block type="niryo_one_joints" id="W5HW1H/JonN#B[1T|{Zd"><data>rad</data><value name="j1"><block type="math_number" id="bWV.CTn+n:9XV23$g453"><field name="NUM">-0.081</field></block></value><value name="j2"><block type="math_number" id="gtD#lR4Q*MB.vWD;h+=w"><field name="NUM">0.554</field></block></value><value name="j3"><block type="math_number" id="-t:5HUk}(uC!Z$qO}Rjj"><field name="NUM">-0.434</field></block></value><value name="j4"><block type="math_number" id="dd}0bY!,T@+fJ%]cS^CE"><field name="NUM">0.13</field></block></value><value name="j5"><block type="math_number" id="p-44$YRWELjgPN@:ja#7"><field name="NUM">-0.835</field></block></value><value name="j6"><block type="math_number" id="DdY5WOBGabt!~2:YW)yL"><field name="NUM">-0.063</field></block></value></block></value><next><block type="niryo_one_comment" id="g-!}?Nc+^pBmd;F634?W"><field name="COMMENT_TEXT">Conveyor Belt Control</field><next><block type="niryo_one_conveyor_use" id="*UT_[07wU%==*TtEQQ})"><next><block type="niryo_one_conveyor_control" id="kZli=}WadJ!dD$Vdt=bL"><field name="DIRECTION_SELECT">ConveyorDirection.FORWARD</field><value name="CONVEYOR_SWITCH"><block type="niryo_one_conveyor_models" id="LBjsbvcbrP9[#qz(dy!:"><field name="CONVEYOR_SELECT">ConveyorID.ID_1</field></block></value><value name="SPEED_PERCENT"><block type="math_number" id="Tlys.3.!3n@G-6]3;*1~"><field name="NUM">50</field></block></value><next><block type="controls_whileUntil" id=".pk7ebqxv8VW}l!wq:;c"><field name="MODE">WHILE</field><value name="BOOL"><block type="logic_boolean" id="l2.-d/|qCiNd(P%7aM]M"><field name="BOOL">TRUE</field></block></value><statement name="DO"><block type="controls_if" id="2b2FcjNTB[RmoZbNK1k="><value name="IF0"><block type="logic_compare" id="+/7N$(VYIohiPG$m7xcY"><field name="OP">EQ</field><value name="A"><block type="niryo_one_get_digital" id="?7MHinH0(xP[]ox1^aTA"><field name="DIGITAL_ID">DI5</field></block></value><value name="B"><block type="logic_boolean" id="V^KhmcFKzAIiI)hp5|pN"><field name="BOOL">FALSE</field></block></value></block></value><statement name="DO0"><block type="niryo_one_conveyor_stop" id="*2/uMG_u$0Zy1772#Yq)"><value name="CONVEYOR_SWITCH"><block type="niryo_one_conveyor_models" id="@nRpeL5TBQ~Q#9!8+aMH"><field name="CONVEYOR_SELECT">ConveyorID.ID_1</field></block></value><next><block type="niryo_one_sleep" id="C|R8QT(C8sh45)yw/]Tp"><value name="SLEEP_TIME"><block type="math_number" id="HJCC#6x^iund3%{l8^dP"><field name="NUM">1</field></block></value><next><block type="niryo_one_comment" id="!qpC5B`-Ly*2pxghK3TC"><field name="COMMENT_TEXT">Intermediate position for picking up objects</field><next><block type="niryo_one_move_joints_from_joints" id="yA$RfRsMoqscOboUeNFk"><value name="JOINTS"><block type="niryo_one_joints" id="0D,?,ds279)HJ(:$d?#C"><data>rad</data><value name="j1"><block type="math_number" id="?D)-;R7ZZD:~#13p)s{}"><field name="NUM">-0.075</field></block></value><value name="j2"><block type="math_number" id="WiSSl?ab8?,Mzo1TX_FC"><field name="NUM">0.381</field></block></value><value name="j3"><block type="math_number" id=":T#3jqp0}i_o(jl9#n8s"><field name="NUM">-0.59</field></block></value><value name="j4"><block type="math_number" id="IL;D3_Xblbkdr3~.nsZP"><field name="NUM">0.092</field></block></value><value name="j5"><block type="math_number" id="eM4qBuK;S%F*L}Hx3?=v"><field name="NUM">-1.391</field></block></value><value name="j6"><block type="math_number" id="0%N#8_i|DOeieUNOJ5}{"><field name="NUM">-0.204</field></block></value></block></value><next><block type="niryo_one_open_gripper" id="u}qcUV3VZGsrE]XhLC8U"><field name="OPEN_SPEED">250</field><next><block type="niryo_one_comment" id="#jjoB1PZ/kkO`WQ|FCQ0"><field name="COMMENT_TEXT">PICK Position</field><next><block type="niryo_one_move_pose_from_pose" id="1!b^xv{CcR-@9O5uy~Uo"><field name="MOVE_POSE_METHOD_SELECT">MoveCommandType.POSE</field><value name="POSE"><block type="niryo_one_pose" id="Ho8GYL}+:G5=z?.|aC{|"><data>rad</data><value name="x"><block type="math_number" id="-kP^/P~X_Z/H*?O+%XhQ"><field name="NUM">0.227</field></block></value><value name="y"><block type="math_number" id="85LAFm~3NlWDX{cfm~4W"><field name="NUM">-0.17</field></block></value><value name="z"><block type="math_number" id="L1t$p%7wd%)57j$aPjL`"><field name="NUM">0.062</field></block></value><value name="roll"><block type="math_number" id="gVQC%`N,SG0rnIuo!aND"><field name="NUM">-2.761</field></block></value><value name="pitch"><block type="math_number" id="CVy1YPKtgP-CP}~y!KG$"><field name="NUM">1.495</field></block></value><value name="yaw"><block type="math_number" id="%,4{7Eb(l#=SnwUQn_4:"><field name="NUM">-2.767</field></block></value></block></value><next><block type="niryo_one_close_gripper" id="m~OBXEtxWB~LeEGkptU8"><field name="CLOSE_SPEED">250</field><next><block type="niryo_one_comment" id="V%SNl9fk*%3VsvaP3!OQ"><field name="COMMENT_TEXT">Intermediate Position for placing object</field><next><block type="niryo_one_move_joints_from_joints" id="dSVU::)$$o:zi~Qy)_o;"><value name="JOINTS"><block type="niryo_one_joints" id=":rv,VxotS/$rKYL3jW.$"><data>rad</data><value name="j1"><block type="math_number" id="pad#RT4Y_[cP%qU[?r,P"><field name="NUM">-1.252</field></block></value><value name="j2"><block type="math_number" id="QE@B*Yhe^/m:c)t|A?hA"><field name="NUM">-0.046</field></block></value><value name="j3"><block type="math_number" id="NB1YZuhUwTX{Cy7u@S-7"><field name="NUM">-0.042</field></block></value><value name="j4"><block type="math_number" id="_L|%IT)o]af}V9RP[|%="><field name="NUM">-0.043</field></block></value><value name="j5"><block type="math_number" id="%jRet:L9FiDRlziBnzV/"><field name="NUM">-1.259</field></block></value><value name="j6"><block type="math_number" id="v|Lmec=pjG}Coz@V;HG="><field name="NUM">-0.687</field></block></value></block></value><next><block type="niryo_one_comment" id="xz?kE_~Z5+R:N`{$4!ay"><field name="COMMENT_TEXT">Place position</field><next><block type="niryo_one_move_pose_from_pose" id="/pNOefOkHZ9)_p0y[fW4"><field name="MOVE_POSE_METHOD_SELECT">MoveCommandType.POSE</field><value name="POSE"><block type="niryo_one_pose" id="6WFA,]gRN!/#Sroh)ZgL"><data>rad</data><value name="x"><block type="math_number" id="k!{q`WQ[Npv.f7Nm9qS("><field name="NUM">-0.012</field></block></value><value name="y"><block type="math_number" id="PTM#?CoY`iBY=xF;EZ-:"><field name="NUM">-0.251</field></block></value><value name="z"><block type="math_number" id="~t}MNszcv]vdDc)uAap6"><field name="NUM">0.055</field></block></value><value name="roll"><block type="math_number" id="_dAf:u9IFh]2YWY;tH-w"><field name="NUM">-3.124</field></block></value><value name="pitch"><block type="math_number" id="?=eDrCeAECT2|jG,+t~:"><field name="NUM">1.509</field></block></value><value name="yaw"><block type="math_number" id="yyKeU_~@+UhR~B#x]Yku"><field name="NUM">1.632</field></block></value></block></value><next><block type="niryo_one_sleep" id="0w*O;I*BW_Ju#@*M{kNf"><value name="SLEEP_TIME"><block type="math_number" id="xy`j;h.H;nFHH:$#rS[b"><field name="NUM">1</field></block></value><next><block type="niryo_one_open_gripper" id="zD9L,`%1H`2487}k+HVq"><field name="OPEN_SPEED">250</field><next><block type="niryo_one_sleep" id="D/Z8#Y(K@/*,.SBnO*ok"><value name="SLEEP_TIME"><block type="math_number" id="mb;DgbE*N)?uXt#]Xiy?"><field name="NUM">1</field></block></value><next><block type="niryo_one_conveyor_stop" id="7tG;)(OhEg0Tk)fcO1PN"><value name="CONVEYOR_SWITCH"><block type="niryo_one_conveyor_models" id="]v!Nv$J-yGW8en~eo^0@"><field name="CONVEYOR_SELECT">ConveyorID.ID_1</field></block></value><next><block type="niryo_one_sleep" id="NX:}VLA{c}[Jlk}CHsk."><value name="SLEEP_TIME"><block type="math_number" id="nw*6=!6e/gPq`X(|Ki7*"><field name="NUM">3</field></block></value><next><block type="niryo_one_comment" id="Yy|EThdfh{t7j%b9@g;%"><field name="COMMENT_TEXT">Restart Conveyor</field><next><block type="niryo_one_conveyor_control" id="xY%m{R4x}~$bURnn{*}J"><field name="DIRECTION_SELECT">ConveyorDirection.FORWARD</field><value name="CONVEYOR_SWITCH"><block type="niryo_one_conveyor_models" id="zz@p)8}pkc|}[oMAB57$"><field name="CONVEYOR_SELECT">ConveyorID.ID_1</field></block></value><value name="SPEED_PERCENT"><block type="math_number" id="LTp@{L2T|MJyHB{Ss]}H"><field name="NUM">50</field></block></value></block></next></block></next></block></next></block></next></block></next></block></next></block></next></block></next></block></next></block></next></block></next></block></next></block></next></block></next></block></next></block></next></block></next></block></next></block></statement><next><block type="controls_if" id="y]Bu+0erQ#paQ#Ac7yxT"><value name="IF0"><block type="logic_compare" id="=,w$S(Kq|f,Qd23=`Rj0"><field name="OP">EQ</field><value name="A"><block type="niryo_one_get_digital" id="75Ef9[cQc8Gb?oTx.*W$"><field name="DIGITAL_ID">DI5</field></block></value><value name="B"><block type="logic_boolean" id="P{_p}}QIn6J(2kKys0jH"><field name="BOOL">FALSE</field></block></value></block></value><statement name="DO0"><block type="niryo_one_conveyor_stop" id=".o*E7.S%q(.;ro]e1k@,"><value name="CONVEYOR_SWITCH"><block type="niryo_one_conveyor_models" id="L[-9tvEF(L7ed2yY?5Zv"><field name="CONVEYOR_SELECT">ConveyorID.ID_1</field></block></value><next><block type="niryo_one_sleep" id="F8$ziR(L(2Q|nA=avtf1"><value name="SLEEP_TIME"><block type="math_number" id="VkyMlsv9@?-+NoRz$G.M"><field name="NUM">1</field></block></value><next><block type="niryo_one_comment" id="w.|~nGWtgoJ$d+fWWGZK"><field name="COMMENT_TEXT">Intermediate position for picking up objects</field><next><block type="niryo_one_move_joints_from_joints" id="X9nj=$Fbo7A|3R1EpSgw"><value name="JOINTS"><block type="niryo_one_joints" id="u5r@p#G@j63Ph4_|hV-j"><data>rad</data><value name="j1"><block type="math_number" id="gmVi]u#Xf5G1waV6zx[K"><field name="NUM">-0.075</field></block></value><value name="j2"><block type="math_number" id="BMbq1],n=;-E@EmZ+TS)"><field name="NUM">0.381</field></block></value><value name="j3"><block type="math_number" id="%%2%f-D9+,fGMk[W4o*X"><field name="NUM">-0.59</field></block></value><value name="j4"><block type="math_number" id="]X7k1^!}c+Z1Z=RR}y,6"><field name="NUM">0.092</field></block></value><value name="j5"><block type="math_number" id="VymGw2Q`?=TCH^qTKiaH"><field name="NUM">-1.391</field></block></value><value name="j6"><block type="math_number" id="qXAFRXNPYb=8AhpeMKO%"><field name="NUM">-0.204</field></block></value></block></value><next><block type="niryo_one_open_gripper" id="4n6rq?%*(3znqT}.1g[}"><field name="OPEN_SPEED">250</field><next><block type="niryo_one_comment" id="a%:87r*YU~4|^kZF*m]L"><field name="COMMENT_TEXT">PICK Position</field><next><block type="niryo_one_move_pose_from_pose" id="K.agz.U^/p,th?x$Z3XW"><field name="MOVE_POSE_METHOD_SELECT">MoveCommandType.POSE</field><value name="POSE"><block type="niryo_one_pose" id="~|C`*IAS]-nz;2@Pf$gi"><data>rad</data><value name="x"><block type="math_number" id="b6aqEzh;z#z7i9gy_O]H"><field name="NUM">0.227</field></block></value><value name="y"><block type="math_number" id="e$oOl;|IJjx+7=H)tq1U"><field name="NUM">-0.17</field></block></value><value name="z"><block type="math_number" id="M.R6(1$RU]gyQg1H+`[j"><field name="NUM">0.062</field></block></value><value name="roll"><block type="math_number" id="cm*ElWtWpjb*bl7@=~AR"><field name="NUM">-2.761</field></block></value><value name="pitch"><block type="math_number" id="4xy[KW7w9{TsR7U5f^YG"><field name="NUM">1.495</field></block></value><value name="yaw"><block type="math_number" id="v7-uj=mJZA-IvYePB;Ea"><field name="NUM">-2.767</field></block></value></block></value><next><block type="niryo_one_close_gripper" id="BxS{y%qIbndzds5=+OMG"><field name="CLOSE_SPEED">250</field><next><block type="niryo_one_comment" id="v!(Jy~xFrlqnz}gFAT/j"><field name="COMMENT_TEXT">Intermediate Position for placing object</field><next><block type="niryo_one_move_joints_from_joints" id="WHB;nf4X*OFCNY4oD1(Y"><value name="JOINTS"><block type="niryo_one_joints" id="{_m,0CJN3ejWCVy?`k29"><data>rad</data><value name="j1"><block type="math_number" id="C06=l0ala26$zX5,T?MN"><field name="NUM">-1.252</field></block></value><value name="j2"><block type="math_number" id="*YT2Vne54*1M4;^KB|eF"><field name="NUM">-0.046</field></block></value><value name="j3"><block type="math_number" id=",_aytB[,l-;,|KdIho:R"><field name="NUM">-0.042</field></block></value><value name="j4"><block type="math_number" id="y(K*RBeV]2na?go!dg^."><field name="NUM">-0.043</field></block></value><value name="j5"><block type="math_number" id="lhfiT(cRe.*D(!O]+E,S"><field name="NUM">-1.259</field></block></value><value name="j6"><block type="math_number" id="z%d3$Tb_!xwT/2Wok1Yn"><field name="NUM">-0.687</field></block></value></block></value><next><block type="niryo_one_comment" id="0h-k^)j-/9j0O)$S!!Bj"><field name="COMMENT_TEXT">Place position</field><next><block type="niryo_one_move_pose_from_pose" id=")%Rboaa+0;WyMXaG5%4X"><field name="MOVE_POSE_METHOD_SELECT">MoveCommandType.POSE</field><value name="POSE"><block type="niryo_one_pose" id="=K/BS-k4t:a?*Dvs/-tM"><data>rad</data><value name="x"><block type="math_number" id="rL499r819tw38[w9puH*"><field name="NUM">-0.034</field></block></value><value name="y"><block type="math_number" id="!aTOs_k0u[AMyv:gf-:J"><field name="NUM">-0.248</field></block></value><value name="z"><block type="math_number" id="BK9jOaNaMzm8J^@z;AMz"><field name="NUM">0.053</field></block></value><value name="roll"><block type="math_number" id="hm}}r$TF?f`^sKa?;Gj!"><field name="NUM">-3.097</field></block></value><value name="pitch"><block type="math_number" id="Wwp2=UD7:,#@h`RC3qJ)"><field name="NUM">1.503</field></block></value><value name="yaw"><block type="math_number" id="K,qxpjSV{t#r~=]}$;,Q"><field name="NUM">1.575</field></block></value></block></value><next><block type="niryo_one_sleep" id="ZQ%pIJ%[J,gd+]Vxm;;K"><value name="SLEEP_TIME"><block type="math_number" id="AycY*$yPA!dn2q*VF!J?"><field name="NUM">1</field></block></value><next><block type="niryo_one_open_gripper" id="}qFJ81+/2Qkfl{UKG}EJ"><field name="OPEN_SPEED">250</field><next><block type="niryo_one_sleep" id="C%UxHV|=SMFMq1GD:,E="><value name="SLEEP_TIME"><block type="math_number" id="7dFzh.{Th`]+JvMW~C[,"><field name="NUM">1</field></block></value><next><block type="niryo_one_conveyor_stop" id="5AaYYp2Q)w{#M.EqpEJ:"><value name="CONVEYOR_SWITCH"><block type="niryo_one_conveyor_models" id="(SH{+nk^{d^sH[P-|OU="><field name="CONVEYOR_SELECT">ConveyorID.ID_1</field></block></value><next><block type="niryo_one_sleep" id="ym7yP6w)#VJ!@(eJQdBf"><value name="SLEEP_TIME"><block type="math_number" id="5++*^iefY9R9P9Dr[5u9"><field name="NUM">3</field></block></value><next><block type="niryo_one_comment" id="s4]tl`b!xK^rozwG||-K"><field name="COMMENT_TEXT">Restart Conveyor</field><next><block type="niryo_one_conveyor_control" id="PA-/?k~H)DqF!c~,N*/B"><field name="DIRECTION_SELECT">ConveyorDirection.FORWARD</field><value name="CONVEYOR_SWITCH"><block type="niryo_one_conveyor_models" id="}Sux5$=`I!FhXPnleiXO"><field name="CONVEYOR_SELECT">ConveyorID.ID_1</field></block></value><value name="SPEED_PERCENT"><block type="math_number" id="r`W*d`1K7Rk)MW/BGT|%"><field name="NUM">50</field></block></value></block></next></block></next></block></next></block></next></block></next></block></next></block></next></block></next></block></next></block></next></block></next></block></next></block></next></block></next></block></next></block></next></block></next></block></next></block></statement><next><block type="controls_if" id="33g9YrzJ7{zI5NX}%Jqh"><value name="IF0"><block type="logic_compare" id="p/D.r{u$=.;OyzeXNz]v"><field name="OP">EQ</field><value name="A"><block type="niryo_one_get_digital" id="usc)qz8l0+6JepF=wAS{"><field name="DIGITAL_ID">DI5</field></block></value><value name="B"><block type="logic_boolean" id="K7dVsVhHoo+NU|!TN,A~"><field name="BOOL">FALSE</field></block></value></block></value><statement name="DO0"><block type="niryo_one_conveyor_stop" id="^VA)ji#$W%xm%+tW/Sx;"><value name="CONVEYOR_SWITCH"><block type="niryo_one_conveyor_models" id="u;%2`K;G3;[6io=(Jp0`"><field name="CONVEYOR_SELECT">ConveyorID.ID_1</field></block></value><next><block type="niryo_one_sleep" id="OC3fJf6X49^acI-2M--p"><value name="SLEEP_TIME"><block type="math_number" id="rI;):W7m$B,8h|yX#1q-"><field name="NUM">1</field></block></value><next><block type="niryo_one_comment" id="FUw1b}5GIJbk3QQ1;BP]"><field name="COMMENT_TEXT">Intermediate position for picking up objects</field><next><block type="niryo_one_move_joints_from_joints" id="f[Yh*d7vUjmWDs$G7{QF"><value name="JOINTS"><block type="niryo_one_joints" id="k_Zoi+ZT_XYp[U;xaAlV"><data>rad</data><value name="j1"><block type="math_number" id="iE10ySY+Hy]2@{7T5=|Z"><field name="NUM">-0.075</field></block></value><value name="j2"><block type="math_number" id="m%7)Uu+9OpBs!*k.`??K"><field name="NUM">0.381</field></block></value><value name="j3"><block type="math_number" id="HT$qMrKvsdU}fHgM;[0]"><field name="NUM">-0.59</field></block></value><value name="j4"><block type="math_number" id=":.FKR+v)tA1Y`X/.,K2B"><field name="NUM">0.092</field></block></value><value name="j5"><block type="math_number" id="C*84Y!{$xR3]7ik4ZY{Y"><field name="NUM">-1.391</field></block></value><value name="j6"><block type="math_number" id="{,7ZQ(96}l-9H.{qhsLX"><field name="NUM">-0.204</field></block></value></block></value><next><block type="niryo_one_open_gripper" id="|pN,aH|3rck67bVofGVj"><field name="OPEN_SPEED">250</field><next><block type="niryo_one_comment" id="ea7W6Isg21C!ln#x{}6n"><field name="COMMENT_TEXT">PICK Position</field><next><block type="niryo_one_move_pose_from_pose" id="^%JTO5A#ZkrO$$vJXnHh"><field name="MOVE_POSE_METHOD_SELECT">MoveCommandType.POSE</field><value name="POSE"><block type="niryo_one_pose" id="z4EYCe|n4zm~I-FbsgJh"><data>rad</data><value name="x"><block type="math_number" id="t^VGdX-G?v=B6]Y[|`vd"><field name="NUM">0.227</field></block></value><value name="y"><block type="math_number" id="Dq5s5H.U]+!2Q}rcc#,%"><field name="NUM">-0.17</field></block></value><value name="z"><block type="math_number" id="EFhm5lhOT$FOp-wql]UG"><field name="NUM">0.062</field></block></value><value name="roll"><block type="math_number" id="|28dk$]$+dhO)h;JQF83"><field name="NUM">-2.761</field></block></value><value name="pitch"><block type="math_number" id="~u0vPSvO34DMKj{#[aUI"><field name="NUM">1.495</field></block></value><value name="yaw"><block type="math_number" id="Je5()p2sZ5eJUu|l-pq+"><field name="NUM">-2.767</field></block></value></block></value><next><block type="niryo_one_close_gripper" id="A1XMs?5aY{m8-V0`X!f3"><field name="CLOSE_SPEED">250</field><next><block type="niryo_one_comment" id="rx9]rw$Ki%@!vqV_l5()"><field name="COMMENT_TEXT">Intermediate Position for placing object</field><next><block type="niryo_one_move_joints_from_joints" id="Hk(?4*Wu0qNtz9U?]OX@"><value name="JOINTS"><block type="niryo_one_joints" id="]mJ/$axqXZOVrH=M|}w!"><data>rad</data><value name="j1"><block type="math_number" id="S}1L]7MegEP6aFycxtJ*"><field name="NUM">-1.252</field></block></value><value name="j2"><block type="math_number" id="a+9^$`Wc@AmC#fq:$4Z3"><field name="NUM">-0.046</field></block></value><value name="j3"><block type="math_number" id="DolxoI(!nmW$XS-Fu_$#"><field name="NUM">-0.042</field></block></value><value name="j4"><block type="math_number" id="AbMMujqK2^]%jJrE}oGf"><field name="NUM">-0.043</field></block></value><value name="j5"><block type="math_number" id="[8ssq/yfC/9==ZQ10$zQ"><field name="NUM">-1.259</field></block></value><value name="j6"><block type="math_number" id="n/T#*Snsn*c(`gqC)Tjs"><field name="NUM">-0.687</field></block></value></block></value><next><block type="niryo_one_comment" id="zTK+,~zh]+rE$l:Y,:WF"><field name="COMMENT_TEXT">Place position</field><next><block type="niryo_one_move_pose_from_pose" id="kKYXFT%pXA3[oY*`^7Oo"><field name="MOVE_POSE_METHOD_SELECT">MoveCommandType.POSE</field><value name="POSE"><block type="niryo_one_pose" id="$QZF4mn1h{KSn{vqOd.`"><data>rad</data><value name="x"><block type="math_number" id="op{h+E(8};?w_JXY)-uR"><field name="NUM">-0.063</field></block></value><value name="y"><block type="math_number" id="(9?*0B{_T/o*9}t6f1Vw"><field name="NUM">-0.242</field></block></value><value name="z"><block type="math_number" id="9{xMv)^WdZC.)4xYbb#v"><field name="NUM">0.051</field></block></value><value name="roll"><block type="math_number" id="wVs,zZJ.E:j{0:,/H=y8"><field name="NUM">-2.546</field></block></value><value name="pitch"><block type="math_number" id="J!{rByUe!B@t2$x-e?L#"><field name="NUM">1.469</field></block></value><value name="yaw"><block type="math_number" id="Ck;ZF~ErO#?qGS-B2myw"><field name="NUM">2.121</field></block></value></block></value><next><block type="niryo_one_sleep" id="}_x+t%1Fybcoy{)cflx|"><value name="SLEEP_TIME"><block type="math_number" id="+FPz%?TsW@v3BzK$;bT1"><field name="NUM">1</field></block></value><next><block type="niryo_one_open_gripper" id="--52i*}%n5w|@,~.,%J["><field name="OPEN_SPEED">250</field><next><block type="niryo_one_sleep" id=":?No.$49eJ^qskka;tNe"><value name="SLEEP_TIME"><block type="math_number" id="X}Aak1}1H.cy+aN:9?2z"><field name="NUM">1</field></block></value><next><block type="niryo_one_conveyor_stop" id="*u!joih#Z}7c/faT=zs+"><value name="CONVEYOR_SWITCH"><block type="niryo_one_conveyor_models" id="jnZV}o,ex?D}MLsz-aZ^"><field name="CONVEYOR_SELECT">ConveyorID.ID_1</field></block></value><next><block type="niryo_one_sleep" id="K=]+4V}Hi=CAW]zI$dk("><value name="SLEEP_TIME"><block type="math_number" id="|=7K^p9{6nsAj]~3/vqE"><field name="NUM">3</field></block></value><next><block type="niryo_one_comment" id="Ej357}m`(s.HB.UtS*T4"><field name="COMMENT_TEXT">Restart Conveyor</field><next><block type="niryo_one_conveyor_control" id="Y:g5y$yJ;YMJ3Ib^d^.t"><field name="DIRECTION_SELECT">ConveyorDirection.FORWARD</field><value name="CONVEYOR_SWITCH"><block type="niryo_one_conveyor_models" id="XlGeQ;eUZ_Rrf|jv!VK$"><field name="CONVEYOR_SELECT">ConveyorID.ID_1</field></block></value><value name="SPEED_PERCENT"><block type="math_number" id="1+Q=.JTMw(km0GEja~%X"><field name="NUM">50</field></block></value></block></next></block></next></block></next></block></next></block></next></block></next></block></next></block></next></block></next></block></next></block></next></block></next></block></next></block></next></block></next></block></next></block></next></block></next></block></statement></block></next></block></next></block></statement></block></next></block></next></block></next></block></next></block></next></block></xml>